./.gitignore
./PKG-INFO
./README.md
./py.typed
./pyproject.toml
./examples/qwen_vl_example/README.md
./examples/qwen_vl_example/__init__.py
./examples/qwen_vl_example/pyproject.toml
./examples/qwen_vl_example/qwen_vl_example.py
./tests/test_chat_completions.py
./tests/test_openai_llm.py
./tests/test_openai_realtime.py
./tests/test_tts_openai.py
./vision_agents/plugins/openai/__init__.py
./vision_agents/plugins/openai/events.py
./vision_agents/plugins/openai/openai_llm.py
./vision_agents/plugins/openai/openai_realtime.py
./vision_agents/plugins/openai/rtc_manager.py
./vision_agents/plugins/openai/tool_utils.py
./vision_agents/plugins/openai/tts.py
./vision_agents/plugins/openai/chat_completions/__init__.py
./vision_agents/plugins/openai/chat_completions/chat_completions_llm.py
./vision_agents/plugins/openai/chat_completions/chat_completions_vlm.py
vision_agents_plugins_openai-0.2.10.dist-info/METADATA
vision_agents_plugins_openai-0.2.10.dist-info/WHEEL
vision_agents_plugins_openai-0.2.10.dist-info/RECORD
