Metadata-Version: 2.4
Name: vision-agents-plugins-openai
Version: 0.2.10
Summary: OpenAI plugin for vision agents
Project-URL: Documentation, https://visionagents.ai/
Project-URL: Website, https://visionagents.ai/
Project-URL: Source, https://github.com/GetStream/Vision-Agents
License-Expression: MIT
Requires-Python: >=3.10
Requires-Dist: openai[realtime]>=2.7.2
Requires-Dist: vision-agents
